aware_terminal_providers/__init__.py
aware_terminal_providers/core/__init__.py
aware_terminal_providers/core/descriptor.py
aware_terminal_providers/core/env.py
aware_terminal_providers/core/installer.py
aware_terminal_providers/core/manifest.py
aware_terminal_providers/core/provider_base.py
aware_terminal_providers/core/runners.py
aware_terminal_providers/core/version.py
aware_terminal_providers/providers/__init__.py
aware_terminal_providers/providers/claude_code/__init__.py
aware_terminal_providers/providers/claude_code/adapter.py
aware_terminal_providers/providers/claude_code/metadata.py
aware_terminal_providers/providers/claude_code/releases.json
aware_terminal_providers/providers/codex/__init__.py
aware_terminal_providers/providers/codex/adapter.py
aware_terminal_providers/providers/codex/metadata.py
aware_terminal_providers/providers/codex/releases.json
aware_terminal_providers/providers/codex/session_resolver.py
aware_terminal_providers/providers/gemini/__init__.py
aware_terminal_providers/providers/gemini/adapter.py
aware_terminal_providers/providers/gemini/metadata.py
aware_terminal_providers/providers/gemini/releases.json
aware_terminal_providers-0.1.1.dist-info/METADATA
aware_terminal_providers-0.1.1.dist-info/WHEEL
aware_terminal_providers-0.1.1.dist-info/licenses/LICENSE
aware_terminal_providers-0.1.1.dist-info/RECORD
