Metadata-Version: 2.4
Name: aware-terminal-providers
Version: 0.1.1
Summary: Provider registry and automation helpers for aware-terminal.
Author-email: Luis Lechuga <luis@aware-agent.com>
License: MIT License
License-File: LICENSE
Requires-Python: >=3.12
Requires-Dist: pydantic<3.0.0,>=2.6.0
Provides-Extra: dev
Requires-Dist: black<25.0.0,>=24.8.0; extra == 'dev'
Requires-Dist: flake8<8.0.0,>=7.0.0; extra == 'dev'
Requires-Dist: isort<6.0.0,>=5.13.0; extra == 'dev'
Requires-Dist: pytest<9.0.0,>=8.2.0; extra == 'dev'
Provides-Extra: test
Requires-Dist: pytest-mock<4.0.0,>=3.12.0; extra == 'test'
Requires-Dist: pytest<9.0.0,>=8.2.0; extra == 'test'
